lwcc/LWCC.py
lwcc/__init__.py
lwcc/models/Bay.py
lwcc/models/CSRNet.py
lwcc/models/DMCount.py
lwcc/models/SFANet.py
lwcc/models/__init__.py
lwcc/util/__init__.py
lwcc/util/functions.py
lwcc-0.0.7.dist-info/LICENSE
lwcc-0.0.7.dist-info/METADATA
lwcc-0.0.7.dist-info/WHEEL
lwcc-0.0.7.dist-info/top_level.txt
lwcc-0.0.7.dist-info/RECORD
