Metadata-Version: 2.1
Name: lwcc
Version: 0.0.7
Summary: A LightWeight Crowd Counting library for Python
Home-page: https://github.com/tersekmatija/lwcc
Author: Matija Teršek, Maša Kljun
Author-email: matijatersek@protonmail.com
License: UNKNOWN
Platform: UNKNOWN
Classifier: Programming Language :: Python :: 3
Classifier: License :: OSI Approved :: MIT License
Classifier: Operating System :: OS Independent
Requires-Python: >=3.6
Requires-Dist: numpy (>=1.14.0)
Requires-Dist: torch (>=1.6.0)
Requires-Dist: gdown (>=3.10.1)
Requires-Dist: torchvision (>=0.7.0)
Requires-Dist: Pillow (>=8.0.0)
